<?xml version="1.0" encoding="UTF-8"?>
<files psalm-version="4.16.1@aa7e400908833b10c0333861f86cd48c510b60eb">
  <file src="example/test/AutoReview/FixtureTest.php">
    <ArgumentTypeCoercion occurrences="1">
      <code>$providerClassName</code>
    </ArgumentTypeCoercion>
  </file>
  <file src="example/test/Unit/Entity/UserTest.php">
    <UnnecessaryVarAnnotation occurrences="1">
      <code>Entity\User</code>
    </UnnecessaryVarAnnotation>
  </file>
  <file src="src/FieldDefinition/Reference.php">
    <PropertyTypeCoercion occurrences="1">
      <code>$className</code>
    </PropertyTypeCoercion>
  </file>
  <file src="src/FieldDefinition/References.php">
    <PropertyTypeCoercion occurrences="1">
      <code>$className</code>
    </PropertyTypeCoercion>
  </file>
  <file src="src/FixtureFactory.php">
    <MissingClosureReturnType occurrences="1">
      <code>function (FieldDefinition\Resolvable $fieldDefinition) {</code>
    </MissingClosureReturnType>
    <MixedAssignment occurrences="1">
      <code>$fieldValue</code>
    </MixedAssignment>
    <TooManyArguments occurrences="1"/>
    <UnnecessaryVarAnnotation occurrences="3">
      <code>EntityDefinition</code>
      <code>ORM\Mapping\ClassMetadata</code>
      <code>array&lt;int, string&gt;</code>
    </UnnecessaryVarAnnotation>
  </file>
  <file src="test/DataProvider/ValueProvider.php">
    <InvalidDocblock occurrences="1">
      <code>public function arbitrary(): \Generator</code>
    </InvalidDocblock>
    <MixedInferredReturnType occurrences="1">
      <code>\Generator&lt;string, array&lt;string[], bool, float, int, object, \stdClass, string&gt;&gt;</code>
    </MixedInferredReturnType>
  </file>
  <file src="test/Double/Faker/FalseGenerator.php">
    <MissingParamType occurrences="3">
      <code>$chanceOfGettingTrue</code>
      <code>$max</code>
      <code>$min</code>
    </MissingParamType>
    <MixedArgument occurrences="2">
      <code>$max</code>
      <code>$min</code>
    </MixedArgument>
    <ParamNameMismatch occurrences="2">
      <code>$max</code>
      <code>$min</code>
    </ParamNameMismatch>
  </file>
  <file src="test/Double/Faker/MaximumGenerator.php">
    <MissingParamType occurrences="2">
      <code>$max</code>
      <code>$min</code>
    </MissingParamType>
    <MixedInferredReturnType occurrences="1">
      <code>int</code>
    </MixedInferredReturnType>
    <MixedReturnStatement occurrences="1">
      <code>$max</code>
    </MixedReturnStatement>
    <ParamNameMismatch occurrences="2">
      <code>$max</code>
      <code>$min</code>
    </ParamNameMismatch>
  </file>
  <file src="test/Double/Faker/MinimumGenerator.php">
    <MissingParamType occurrences="2">
      <code>$max</code>
      <code>$min</code>
    </MissingParamType>
    <MixedInferredReturnType occurrences="1">
      <code>int</code>
    </MixedInferredReturnType>
    <MixedReturnStatement occurrences="1">
      <code>$min</code>
    </MixedReturnStatement>
    <ParamNameMismatch occurrences="2">
      <code>$max</code>
      <code>$min</code>
    </ParamNameMismatch>
  </file>
  <file src="test/Double/Faker/TrueGenerator.php">
    <MissingParamType occurrences="3">
      <code>$chanceOfGettingTrue</code>
      <code>$max</code>
      <code>$min</code>
    </MissingParamType>
    <MixedArgument occurrences="2">
      <code>$max</code>
      <code>$min</code>
    </MixedArgument>
    <ParamNameMismatch occurrences="2">
      <code>$max</code>
      <code>$min</code>
    </ParamNameMismatch>
  </file>
  <file src="test/Integration/FixtureFactoryTest.php">
    <InternalMethod occurrences="1">
      <code>addToAssertionCount</code>
    </InternalMethod>
  </file>
  <file src="test/Unit/EntityDefinitionTest.php">
    <MissingClosureParamType occurrences="2">
      <code>$entity</code>
      <code>$entity</code>
    </MissingClosureParamType>
    <MixedArgumentTypeCoercion occurrences="1">
      <code>$fieldDefinitions</code>
    </MixedArgumentTypeCoercion>
    <UnusedClosureParam occurrences="4">
      <code>$entity</code>
      <code>$entity</code>
      <code>$fieldValues</code>
      <code>$fieldValues</code>
    </UnusedClosureParam>
  </file>
  <file src="test/Unit/FieldDefinition/ClosureTest.php">
    <UnusedClosureParam occurrences="1">
      <code>$faker</code>
    </UnusedClosureParam>
  </file>
  <file src="test/Unit/FieldDefinition/ReferencesTest.php">
    <RedundantCondition occurrences="1">
      <code>assertIsArray</code>
    </RedundantCondition>
  </file>
  <file src="test/Unit/FieldDefinition/ValueTest.php">
    <MixedAssignment occurrences="1">
      <code>$resolved</code>
    </MixedAssignment>
  </file>
  <file src="test/Unit/FieldDefinitionTest.php">
    <UnnecessaryVarAnnotation occurrences="2">
      <code>Entity\User</code>
      <code>Entity\User</code>
    </UnnecessaryVarAnnotation>
    <UnusedClosureParam occurrences="2">
      <code>$faker</code>
      <code>$faker</code>
    </UnusedClosureParam>
  </file>
  <file src="test/Unit/FixtureFactory/UsingDefaultStrategyTest.php">
    <UnnecessaryVarAnnotation occurrences="22">
      <code>Entity\Organization</code>
      <code>Entity\Organization</code>
      <code>Entity\Organization</code>
      <code>Entity\Organization</code>
      <code>Entity\Repository</code>
      <code>Entity\Repository</code>
      <code>Entity\Repository</code>
      <code>Entity\Repository</code>
      <code>Entity\Repository</code>
      <code>Entity\Repository</code>
      <code>Entity\Repository</code>
      <code>Entity\Repository</code>
      <code>Entity\User</code>
      <code>Entity\User</code>
      <code>Entity\User</code>
      <code>Entity\User</code>
      <code>Entity\User</code>
      <code>Entity\User</code>
      <code>Entity\User</code>
      <code>Entity\User</code>
      <code>Entity\User</code>
      <code>Entity\User</code>
    </UnnecessaryVarAnnotation>
    <UnusedClosureParam occurrences="4">
      <code>$faker</code>
      <code>$faker</code>
      <code>$faker</code>
      <code>$faker</code>
    </UnusedClosureParam>
  </file>
  <file src="test/Unit/FixtureFactory/UsingWithOptionalStrategyTest.php">
    <UnnecessaryVarAnnotation occurrences="24">
      <code>Entity\Organization</code>
      <code>Entity\Organization</code>
      <code>Entity\Organization</code>
      <code>Entity\Organization</code>
      <code>Entity\Repository</code>
      <code>Entity\Repository</code>
      <code>Entity\Repository</code>
      <code>Entity\Repository</code>
      <code>Entity\Repository</code>
      <code>Entity\Repository</code>
      <code>Entity\Repository</code>
      <code>Entity\Repository</code>
      <code>Entity\User</code>
      <code>Entity\User</code>
      <code>Entity\User</code>
      <code>Entity\User</code>
      <code>Entity\User</code>
      <code>Entity\User</code>
      <code>Entity\User</code>
      <code>Entity\User</code>
      <code>Entity\User</code>
      <code>Entity\User</code>
      <code>Entity\User</code>
      <code>Entity\User</code>
    </UnnecessaryVarAnnotation>
    <UnusedClosureParam occurrences="4">
      <code>$faker</code>
      <code>$faker</code>
      <code>$faker</code>
      <code>$faker</code>
    </UnusedClosureParam>
  </file>
  <file src="test/Unit/FixtureFactory/UsingWithoutOptionalStrategyTest.php">
    <UnnecessaryVarAnnotation occurrences="24">
      <code>Entity\Organization</code>
      <code>Entity\Organization</code>
      <code>Entity\Organization</code>
      <code>Entity\Organization</code>
      <code>Entity\Repository</code>
      <code>Entity\Repository</code>
      <code>Entity\Repository</code>
      <code>Entity\Repository</code>
      <code>Entity\Repository</code>
      <code>Entity\Repository</code>
      <code>Entity\Repository</code>
      <code>Entity\Repository</code>
      <code>Entity\User</code>
      <code>Entity\User</code>
      <code>Entity\User</code>
      <code>Entity\User</code>
      <code>Entity\User</code>
      <code>Entity\User</code>
      <code>Entity\User</code>
      <code>Entity\User</code>
      <code>Entity\User</code>
      <code>Entity\User</code>
      <code>Entity\User</code>
      <code>Entity\User</code>
    </UnnecessaryVarAnnotation>
    <UnusedClosureParam occurrences="4">
      <code>$faker</code>
      <code>$faker</code>
      <code>$faker</code>
      <code>$faker</code>
    </UnusedClosureParam>
  </file>
  <file src="test/Unit/FixtureFactoryTest.php">
    <ArgumentTypeCoercion occurrences="1">
      <code>$className</code>
    </ArgumentTypeCoercion>
    <MixedArgument occurrences="2">
      <code>$fieldValues['name']</code>
      <code>$name</code>
    </MixedArgument>
    <RedundantCondition occurrences="2">
      <code>assertNotNull</code>
      <code>assertNotNull</code>
    </RedundantCondition>
    <UnnecessaryVarAnnotation occurrences="23">
      <code>Entity\Organization</code>
      <code>Entity\Organization</code>
      <code>Entity\Organization</code>
      <code>Entity\Organization</code>
      <code>Entity\Organization</code>
      <code>Entity\Organization</code>
      <code>Entity\Organization</code>
      <code>Entity\Organization</code>
      <code>Entity\Organization</code>
      <code>Entity\Organization</code>
      <code>Entity\Organization</code>
      <code>Entity\Organization</code>
      <code>Entity\Organization</code>
      <code>Entity\Project</code>
      <code>Entity\Repository</code>
      <code>Entity\Repository</code>
      <code>Entity\Repository</code>
      <code>Entity\Repository</code>
      <code>Entity\Repository</code>
      <code>Entity\Repository</code>
      <code>Entity\Repository</code>
      <code>Entity\User</code>
      <code>Entity\User</code>
    </UnnecessaryVarAnnotation>
    <UnusedClosureParam occurrences="1">
      <code>$user</code>
    </UnusedClosureParam>
    <UnusedVariable occurrences="1">
      <code>$name</code>
    </UnusedVariable>
  </file>
  <file src="test/Unit/Strategy/DefaultStrategyTest.php">
    <MixedAssignment occurrences="2">
      <code>$expected</code>
      <code>$resolved</code>
    </MixedAssignment>
  </file>
  <file src="test/Unit/Strategy/WithOptionalStrategyTest.php">
    <MixedAssignment occurrences="4">
      <code>$expected</code>
      <code>$expected</code>
      <code>$resolved</code>
      <code>$resolved</code>
    </MixedAssignment>
  </file>
</files>
